bigbird/__init__.py
bigbird/helpers.py
bigbird/simple.py
bigbird-0.1.2.dist-info/LICENSE
bigbird-0.1.2.dist-info/METADATA
bigbird-0.1.2.dist-info/WHEEL
bigbird-0.1.2.dist-info/top_level.txt
bigbird-0.1.2.dist-info/RECORD
