Metadata-Version: 2.1
Name: bigbird
Version: 0.1.2
Summary: Genetic Algorithms in Python
Home-page: https://github.com/s2011r2593/big-bird
Author: Sean Rhee
Author-email: seanrhee2024@u.northwestern.edu
License: UNKNOWN
Platform: UNKNOWN
Classifier: Programming Language :: Python :: 3
Classifier: License :: OSI Approved :: MIT License
Classifier: Operating System :: OS Independent
Requires-Python: >=3.8
